neo4j_agent_memory/__init__.py
neo4j_agent_memory/py.typed
neo4j_agent_memory/cli/__init__.py
neo4j_agent_memory/cli/main.py
neo4j_agent_memory/config/__init__.py
neo4j_agent_memory/config/settings.py
neo4j_agent_memory/core/__init__.py
neo4j_agent_memory/core/exceptions.py
neo4j_agent_memory/core/memory.py
neo4j_agent_memory/embeddings/__init__.py
neo4j_agent_memory/embeddings/base.py
neo4j_agent_memory/embeddings/openai.py
neo4j_agent_memory/embeddings/sentence_transformers.py
neo4j_agent_memory/enrichment/__init__.py
neo4j_agent_memory/enrichment/background.py
neo4j_agent_memory/enrichment/base.py
neo4j_agent_memory/enrichment/diffbot.py
neo4j_agent_memory/enrichment/factory.py
neo4j_agent_memory/enrichment/wikimedia.py
neo4j_agent_memory/extraction/__init__.py
neo4j_agent_memory/extraction/base.py
neo4j_agent_memory/extraction/factory.py
neo4j_agent_memory/extraction/gliner_extractor.py
neo4j_agent_memory/extraction/llm_extractor.py
neo4j_agent_memory/extraction/pipeline.py
neo4j_agent_memory/extraction/spacy_extractor.py
neo4j_agent_memory/extraction/streaming.py
neo4j_agent_memory/graph/__init__.py
neo4j_agent_memory/graph/client.py
neo4j_agent_memory/graph/queries.py
neo4j_agent_memory/graph/query_builder.py
neo4j_agent_memory/graph/schema.py
neo4j_agent_memory/integrations/__init__.py
neo4j_agent_memory/integrations/base.py
neo4j_agent_memory/integrations/crewai/__init__.py
neo4j_agent_memory/integrations/crewai/memory.py
neo4j_agent_memory/integrations/langchain/__init__.py
neo4j_agent_memory/integrations/langchain/memory.py
neo4j_agent_memory/integrations/langchain/retriever.py
neo4j_agent_memory/integrations/llamaindex/__init__.py
neo4j_agent_memory/integrations/llamaindex/memory.py
neo4j_agent_memory/integrations/openai_agents/__init__.py
neo4j_agent_memory/integrations/openai_agents/memory.py
neo4j_agent_memory/integrations/openai_agents/tracing.py
neo4j_agent_memory/integrations/pydantic_ai/__init__.py
neo4j_agent_memory-0.0.2.dist-info/METADATA
neo4j_agent_memory-0.0.2.dist-info/WHEEL
neo4j_agent_memory-0.0.2.dist-info/entry_points.txt
neo4j_agent_memory-0.0.2.dist-info/licenses/LICENSE
neo4j_agent_memory-0.0.2.dist-info/RECORD
