Metadata-Version: 2.4
Name: neo4j-agent-memory
Version: 0.0.2
Summary: A comprehensive memory system for AI agents using Neo4j
Project-URL: Homepage, https://github.com/neo4j-labs/agent-memory
Project-URL: Documentation, https://neo4j-agent-memory.vercel.app/
Project-URL: Repository, https://github.com/neo4j-labs/agent-memory
Project-URL: Issues, https://github.com/neo4j-labs/agent-memory/issues
Project-URL: Changelog, https://github.com/neo4j-labs/agent-memory/releases
Author-email: William Lyon <lyonwj@gmail.com>
License: Apache-2.0
License-File: LICENSE
Keywords: agent,ai,context-graph,crewai,knowledge-graph,langchain,llamaindex,llm,memory,neo4j,openai-agents,pydantic-ai,reasoning-memory
Classifier: Development Status :: 4 - Beta
Classifier: Intended Audience :: Developers
Classifier: License :: OSI Approved :: Apache Software License
Classifier: Programming Language :: Python :: 3
Classifier: Programming Language :: Python :: 3.10
Classifier: Programming Language :: Python :: 3.11
Classifier: Programming Language :: Python :: 3.12
Classifier: Programming Language :: Python :: 3.13
Classifier: Topic :: Database :: Front-Ends
Classifier: Topic :: Scientific/Engineering :: Artificial Intelligence
Classifier: Typing :: Typed
Requires-Python: >=3.10
Requires-Dist: neo4j>=5.20.0
Requires-Dist: pydantic-settings>=2.0.0
Requires-Dist: pydantic>=2.0.0
Provides-Extra: all
Requires-Dist: anthropic>=0.20.0; extra == 'all'
Requires-Dist: crewai>=0.50.0; extra == 'all'
Requires-Dist: langchain-core>=0.2.0; extra == 'all'
Requires-Dist: llama-index-core>=0.10.0; extra == 'all'
Requires-Dist: openai>=1.0.0; extra == 'all'
Requires-Dist: pydantic-ai>=0.1.0; extra == 'all'
Requires-Dist: rapidfuzz>=3.0.0; extra == 'all'
Provides-Extra: anthropic
Requires-Dist: anthropic>=0.20.0; extra == 'anthropic'
Provides-Extra: cli
Requires-Dist: click>=8.0.0; extra == 'cli'
Requires-Dist: rich>=13.0.0; extra == 'cli'
Provides-Extra: crewai
Requires-Dist: crewai>=0.50.0; extra == 'crewai'
Provides-Extra: extraction
Requires-Dist: gliner>=0.2.0; extra == 'extraction'
Requires-Dist: spacy>=3.7.0; extra == 'extraction'
Provides-Extra: full
Requires-Dist: anthropic>=0.20.0; extra == 'full'
Requires-Dist: crewai>=0.50.0; extra == 'full'
Requires-Dist: gliner>=0.2.0; extra == 'full'
Requires-Dist: langchain-core>=0.2.0; extra == 'full'
Requires-Dist: llama-index-core>=0.10.0; extra == 'full'
Requires-Dist: openai>=1.0.0; extra == 'full'
Requires-Dist: pydantic-ai>=0.1.0; extra == 'full'
Requires-Dist: rapidfuzz>=3.0.0; extra == 'full'
Requires-Dist: sentence-transformers>=2.2.0; extra == 'full'
Requires-Dist: spacy>=3.7.0; extra == 'full'
Provides-Extra: fuzzy
Requires-Dist: rapidfuzz>=3.0.0; extra == 'fuzzy'
Provides-Extra: gliner
Requires-Dist: gliner>=0.2.0; extra == 'gliner'
Provides-Extra: langchain
Requires-Dist: langchain-core>=0.2.0; extra == 'langchain'
Provides-Extra: llamaindex
Requires-Dist: llama-index-core>=0.10.0; extra == 'llamaindex'
Provides-Extra: observability
Requires-Dist: opentelemetry-api>=1.20.0; extra == 'observability'
Requires-Dist: opentelemetry-sdk>=1.20.0; extra == 'observability'
Provides-Extra: openai
Requires-Dist: openai>=1.0.0; extra == 'openai'
Provides-Extra: openai-agents
Requires-Dist: openai>=1.0.0; extra == 'openai-agents'
Provides-Extra: opentelemetry
Requires-Dist: opentelemetry-api>=1.20.0; extra == 'opentelemetry'
Requires-Dist: opentelemetry-exporter-otlp>=1.20.0; extra == 'opentelemetry'
Requires-Dist: opentelemetry-sdk>=1.20.0; extra == 'opentelemetry'
Provides-Extra: opik
Requires-Dist: opik>=1.0.0; extra == 'opik'
Provides-Extra: pydantic-ai
Requires-Dist: pydantic-ai>=0.1.0; extra == 'pydantic-ai'
Provides-Extra: sentence-transformers
Requires-Dist: sentence-transformers>=2.2.0; extra == 'sentence-transformers'
Provides-Extra: spacy
Requires-Dist: spacy>=3.7.0; extra == 'spacy'
